MANIFEST.in
requirements.txt
setup.py
sat_search.egg-info/PKG-INFO
sat_search.egg-info/SOURCES.txt
sat_search.egg-info/dependency_links.txt
sat_search.egg-info/entry_points.txt
sat_search.egg-info/requires.txt
sat_search.egg-info/top_level.txt
satsearch/__init__.py
satsearch/cli.py
satsearch/config.py
satsearch/search.py
satsearch/version.py
test/__init__.py
test/test_cli.py
test/test_search.py