Metadata-Version: 1.1
Name: sat-search
Version: 0.2.2
Summary: A python client for sat-api
Home-page: https://github.com/sat-utils/sat-search
Author: Matthew Hanson (matthewhanson)
Author-email: matt.a.hanson@gmail.com
License: MIT
Platform: UNKNOWN
Classifier: Framework :: Pytest
Classifier: Topic :: Scientific/Engineering :: GIS
Classifier: Topic :: Scientific/Engineering
Classifier: Intended Audience :: Developers
Classifier: Intended Audience :: Science/Research
Classifier: License :: Freeware
Classifier: Programming Language :: Python :: 2.7
Classifier: Programming Language :: Python :: 3.3
Classifier: Programming Language :: Python :: 3.4
Classifier: Programming Language :: Python :: 3.5
